flask_btsn_alchemy/__init__.py
flask_btsn_alchemy/flask_btsn_alchemy.py
flask_btsn_alchemy/helpers.py
flask_btsn_alchemy/logger.py
flask_btsn_alchemy-0.0.2.dist-info/DESCRIPTION.rst
flask_btsn_alchemy-0.0.2.dist-info/METADATA
flask_btsn_alchemy-0.0.2.dist-info/RECORD
flask_btsn_alchemy-0.0.2.dist-info/WHEEL
flask_btsn_alchemy-0.0.2.dist-info/metadata.json
flask_btsn_alchemy-0.0.2.dist-info/top_level.txt
