Metadata-Version: 2.0
Name: flask-btsn-alchemy
Version: 0.0.2
Summary: BITSON's SQLAlchemy Models
Home-page: https://gitlab.bitson.com.ar/lecovi/flask_btsn_alchemy.git
Author: Leandro E. Colombo Viña
Author-email: colomboleandro@bitson.com.ar
License: AGPL
Platform: any
Classifier: Development Status :: 3 - Alpha
Classifier: Environment :: Web Environment
Classifier: Intended Audience :: Developers
Classifier: License :: OSI Approved :: GNU Affero General Public License v3
Classifier: Operating System :: OS Independent
Classifier: Programming Language :: Python
Classifier: Programming Language :: Python :: 3
Classifier: Topic :: Internet :: WWW/HTTP :: Dynamic Content
Classifier: Topic :: Software Development :: Libraries :: Python Modules
Requires-Dist: Flask
Requires-Dist: Flask-SQLAlchemy
Requires-Dist: rainbow-logging-handler
